[
  {
    "name_short": "Conan Film 1",
    "name": "Detektiv Conan: Der Tickende Wolkenkratzer"
  },
  {
    "name_short": "Conan Film 4",
    "name": "Detektiv Conan: Der Killer in ihren Augen"
  },
  {
    "name_short": "Conan Film 7",
    "name": "Detektiv Conan: Die Kreuzung des Labyrinths"
  },
  {
    "name_short": "Conan Film 12",
    "name": "Detektiv Conan: Die Partitur des Grauens"
  },
  {
    "name_short": "Conan Film 19",
    "name": "Detektiv Conan: Die Sonnenblumen des Infernos"
  },
  {
    "name_short": "Conan Film 20",
    "name": "Detektiv Conan: Der Dunkelste Albtraum"
  },
  {
    "name_short": "Conan Film 21",
    "name": "Detektiv Conan: Der Purpurrote Liebesbrief"
  },
  {
    "name_short": "Conan Film 25",
    "name": "Detektiv Conan: Die Halloween-Braut"
  },
  {
    "name_short": "Conan Film 27",
    "name": "Detektiv Conan: Das 1-Million-Dollar-Pentagramm"
  },
  {
    "name_short": "Professor Layton Film",
    "name": "Professor Layton und die Ewige Diva"
  }
]